{"v":4,"entries":{"общее-кнопка--docs":{"id":"общее-кнопка--docs","title":"Общее/Кнопка","name":"Docs","importPath":"./src/components/button/button.stories.ts","type":"docs","tags":["autodocs","docs"],"storiesImports":[]},"общее-кнопка--default-button":{"type":"story","id":"общее-кнопка--default-button","name":"Default Button","title":"Общее/Кнопка","importPath":"./src/components/button/button.stories.ts","tags":["autodocs","story"]},"общее-кнопка--icon":{"type":"story","id":"общее-кнопка--icon","name":"Icon","title":"Общее/Кнопка","importPath":"./src/components/button/button.stories.ts","tags":["autodocs","story"]},"общее-кнопка-в-корзину--docs":{"id":"общее-кнопка-в-корзину--docs","title":"Общее/Кнопка `В корзину`","name":"Docs","importPath":"./src/components/cart-button/CartButton.stories.tsx","type":"docs","tags":["autodocs","docs"],"storiesImports":[]},"общее-кнопка-в-корзину--default-button":{"type":"story","id":"общее-кнопка-в-корзину--default-button","name":"Default Button","title":"Общее/Кнопка `В корзину`","importPath":"./src/components/cart-button/CartButton.stories.tsx","tags":["autodocs","story"]},"общее-кнопка-в-корзину--icon":{"type":"story","id":"общее-кнопка-в-корзину--icon","name":"Icon","title":"Общее/Кнопка `В корзину`","importPath":"./src/components/cart-button/CartButton.stories.tsx","tags":["autodocs","story"]},"общее-шапка-header--docs":{"id":"общее-шапка-header--docs","title":"Общее/Шапка(header)","name":"Docs","importPath":"./src/components/header/header.stories.tsx","type":"docs","tags":["autodocs","docs"],"storiesImports":[]},"общее-шапка-header--header-with-logo":{"type":"story","id":"общее-шапка-header--header-with-logo","name":"Шапка c лого","title":"Общее/Шапка(header)","importPath":"./src/components/header/header.stories.tsx","tags":["autodocs","story"]},"общее-шапка-header--header-without-logo":{"type":"story","id":"общее-шапка-header--header-without-logo","name":"Шапка без лого","title":"Общее/Шапка(header)","importPath":"./src/components/header/header.stories.tsx","tags":["autodocs","story"]},"общее-каркас-layout--docs":{"id":"общее-каркас-layout--docs","title":"Общее/Каркас(layout)","name":"Docs","importPath":"./src/components/layout/layout.stories.tsx","type":"docs","tags":["autodocs","docs"],"storiesImports":[]},"общее-каркас-layout--layout-with-header":{"type":"story","id":"общее-каркас-layout--layout-with-header","name":"Каркас с шапкой и лого","title":"Общее/Каркас(layout)","importPath":"./src/components/layout/layout.stories.tsx","tags":["autodocs","story"]},"общее-лого--medium-logo":{"type":"story","id":"общее-лого--medium-logo","name":"Лого","title":"Общее/Лого","importPath":"./src/components/logo/logo.stories.tsx","tags":["story"]},"общее-модальное-окно--visible-window":{"type":"story","id":"общее-модальное-окно--visible-window","name":"Видимое модальное окно","title":"Общее/Модальное окно","importPath":"./src/components/modal-window/modal.stories.ts","tags":["story"]},"общее-модальное-окно--invisible-window":{"type":"story","id":"общее-модальное-окно--invisible-window","name":"Скрытое модальное окно","title":"Общее/Модальное окно","importPath":"./src/components/modal-window/modal.stories.ts","tags":["story"]},"общее-карточка-товара--docs":{"id":"общее-карточка-товара--docs","title":"Общее/Карточка товара","name":"Docs","importPath":"./src/components/product-card/ProductCard.stories.tsx","type":"docs","tags":["autodocs","docs"],"storiesImports":[]},"общее-карточка-товара--default-button":{"type":"story","id":"общее-карточка-товара--default-button","name":"Default Button","title":"Общее/Карточка товара","importPath":"./src/components/product-card/ProductCard.stories.tsx","tags":["autodocs","story"]}}}
